fiber/__init__.py
fiber/__main__.py
fiber/core.py
fiber_uploader-3.2.1.dist-info/licenses/LICENSE
fiber_uploader-3.2.1.dist-info/METADATA
fiber_uploader-3.2.1.dist-info/WHEEL
fiber_uploader-3.2.1.dist-info/entry_points.txt
fiber_uploader-3.2.1.dist-info/top_level.txt
fiber_uploader-3.2.1.dist-info/RECORD
