Metadata-Version: 2.4
Name: fiber-uploader
Version: 3.2.1
Summary: A lightweight, zero-dependency PyPI uploader.
Author: Eternals
Classifier: Programming Language :: Python :: 3
Classifier: License :: OSI Approved :: MIT License
Classifier: Operating System :: OS Independent
Requires-Python: >=3.6
License-File: LICENSE
Dynamic: author
Dynamic: classifier
Dynamic: description
Dynamic: description-content-type
Dynamic: license-file
Dynamic: requires-python
Dynamic: summary
